mindconverter/__init__.py
mindconverter/__main__.py
mindconverter/_version.py
mindconverter/ast_edits.py
mindconverter/cli.py
mindconverter/code_analysis.py
mindconverter/config.py
mindconverter/converter.py
mindconverter/forward_call.py
mindconverter/funcs.py
mindconverter/common/__init__.py
mindconverter/common/exceptions.py
mindconverter/common/log.py
mindconverter/graph_based_converter/__init__.py
mindconverter/graph_based_converter/constant.py
mindconverter/graph_based_converter/framework.py
mindconverter/graph_based_converter/report_generator.py
mindconverter/graph_based_converter/common/__init__.py
mindconverter/graph_based_converter/common/code_fragment.py
mindconverter/graph_based_converter/common/global_context.py
mindconverter/graph_based_converter/common/name_mgr.py
mindconverter/graph_based_converter/common/outputs.py
mindconverter/graph_based_converter/common/utils.py
mindconverter/graph_based_converter/common/yapf_config.py
mindconverter/graph_based_converter/generator/__init__.py
mindconverter/graph_based_converter/generator/args_translator.py
mindconverter/graph_based_converter/generator/fragment_utils.py
mindconverter/graph_based_converter/generator/generator.py
mindconverter/graph_based_converter/generator/matcher.py
mindconverter/graph_based_converter/generator/module_struct.py
mindconverter/graph_based_converter/generator/node_struct.py
mindconverter/graph_based_converter/generator/scope_utils.py
mindconverter/graph_based_converter/generator/shared_weights.py
mindconverter/graph_based_converter/mapper/__init__.py
mindconverter/graph_based_converter/mapper/aten_to_ms.json
mindconverter/graph_based_converter/mapper/base.py
mindconverter/graph_based_converter/mapper/onnx_to_ms.json
mindconverter/graph_based_converter/mapper/aten/__init__.py
mindconverter/graph_based_converter/mapper/aten/nn/__init__.py
mindconverter/graph_based_converter/mapper/aten/nn/conv_mapper.py
mindconverter/graph_based_converter/mapper/aten/nn/dropout_mapper.py
mindconverter-1.7.0.dist-info/METADATA
mindconverter-1.7.0.dist-info/WHEEL
mindconverter-1.7.0.dist-info/entry_points.txt
mindconverter-1.7.0.dist-info/top_level.txt
mindconverter-1.7.0.dist-info/RECORD
